{
  "video_path": "Game-1/game1_farright.mp4",
  "model_path": "runs/detect/basketball_yolo11n2/weights/best.pt",
  "fps": 29.97002997002997,
  "frame_count": 11508,
  "duration_seconds": 383.9836,
  "processing_timestamp": "2025-11-05T21:50:37.846146",
  "detection_version": "far_angle_v1",
  "stats": {
    "total_shots": 1,
    "made_shots": 0,
    "missed_shots": 1,
    "undetermined_shots": 0
  },
  "shots": [
    {
      "timestamp_seconds": 380.6803,
      "frame": 11409,
      "outcome": "missed",
      "outcome_reason": "no_vertical_crossing",
      "decision_confidence": 0.75,
      "detection_confidence": 971.5833333333334,
      "frames_in_zone": 12,
      "vertical_passage": false,
      "downward_movement": 63,
      "upward_movement": 3,
      "trajectory_consistency": 0.9545454545454546,
      "ball_final_position": [
        1030,
        225
      ],
      "hoop_position": [
        958,
        264
      ],
      "zone_width": 80,
      "trajectory": [
        {
          "frame": 11409,
          "x": 914,
          "y": 165
        },
        {
          "frame": 11410,
          "x": 921,
          "y": 178
        },
        {
          "frame": 11411,
          "x": 928,
          "y": 192
        },
        {
          "frame": 11412,
          "x": 934,
          "y": 207
        },
        {
          "frame": 11413,
          "x": 940,
          "y": 223
        },
        {
          "frame": 11416,
          "x": 972,
          "y": 225
        },
        {
          "frame": 11417,
          "x": 985,
          "y": 223
        },
        {
          "frame": 11418,
          "x": 995,
          "y": 222
        },
        {
          "frame": 11419,
          "x": 1003,
          "y": 222
        },
        {
          "frame": 11420,
          "x": 1013,
          "y": 222
        },
        {
          "frame": 11421,
          "x": 1024,
          "y": 222
        },
        {
          "frame": 11422,
          "x": 1030,
          "y": 225
        }
      ]
    }
  ],
  "session_info": {
    "detection_method": "far_angle_zone_based",
    "model_path": "runs/detect/basketball_yolo11n2/weights/best.pt",
    "start_time": "2025-11-05T21:50:37.846031"
  }
}